python_object_mapper-0.0.1.dist-info/RECORD
python_object_mapper-0.0.1.dist-info/metadata.json
python_object_mapper-0.0.1.dist-info/WHEEL
python_object_mapper-0.0.1.dist-info/DESCRIPTION.rst
python_object_mapper-0.0.1.dist-info/top_level.txt
python_object_mapper-0.0.1.dist-info/METADATA
pyom/__init__.py
