Metadata-Version: 2.0
Name: python-object-mapper
Version: 0.0.1
Summary: Python Object Mapper
Home-page: https://github.com/python-object-mapper/python-object-mapper
Author: Python Object Mapper
Author-email: maxim@derbin.io
License: MIT
Platform: UNKNOWN
Classifier: License :: OSI Approved :: MIT License
Classifier: Programming Language :: Python
Classifier: Programming Language :: Python :: 3
